pisnrs/Model_seq_cut1_RFC.pkl
pisnrs/__init__.py
pisnrs/seq.pkl
pisnrs-0.0.6.dist-info/METADATA
pisnrs-0.0.6.dist-info/RECORD
pisnrs-0.0.6.dist-info/WHEEL
pisnrs-0.0.6.dist-info/top_level.txt
