Metadata-Version: 2.1
Name: pisnrs
Version: 0.0.6
Summary: A computational server for potential inhibitor and scaffold prediction of nuclear receptors
Home-page: https://github.com/pypa/pisnrs
Author: Dingfeng Wu
Author-email: dfw_bioinfo@126.com
License: UNKNOWN
Platform: UNKNOWN
Classifier: Programming Language :: Python :: 3
Classifier: License :: OSI Approved :: MIT License
Classifier: Operating System :: OS Independent
Requires-Dist: scikit-learn (>=0.19.1)
Requires-Dist: pandas (>=0.23.1)
